licensegh/__init__.py
licensegh/__main__.py
licensegh/cli.py
licensegh/licensegh.py
licensegh-1.1.1.dist-info/METADATA
licensegh-1.1.1.dist-info/WHEEL
licensegh-1.1.1.dist-info/entry_points.txt
licensegh-1.1.1.dist-info/licenses/LICENSE
licensegh-1.1.1.dist-info/RECORD
