Metadata-Version: 2.4
Name: licensegh
Version: 1.1.1
Summary: licensegh is a command line tool that generates a license file for a project from the github open source lincese templates
License: MIT
License-File: LICENSE
Keywords: lincese,choosealicense,licensegh
Author: Saúl Piña
Author-email: sauljabin@gmail.com
Requires-Python: >=3.10,<3.15
Classifier: License :: OSI Approved :: MIT License
Classifier: Environment :: Console
Classifier: Operating System :: MacOS
Classifier: Operating System :: Unix
Classifier: Programming Language :: Python :: 3.10
Classifier: Programming Language :: Python :: 3.11
Classifier: Programming Language :: Python :: 3.12
Classifier: Programming Language :: Python :: 3.13
Classifier: Programming Language :: Python :: 3.14
Requires-Dist: click (>=8)
Requires-Dist: gitpython (>=3)
Requires-Dist: pyyaml (>=6)
Requires-Dist: rich (>=14)
Project-URL: Homepage, https://github.com/sauljabin/licensegh
Project-URL: Repository, https://github.com/sauljabin/licensegh
